hgen/__init__.py
hgen/__main__.py
hgen/_version.py
hgen/injector/__init__.py
hgen/injector/create_proto.py
hgen/injector/headers.py
hgen/proto/__init__.py
hgen/proto/protos.py
hgen/proto/sources.py
hgen/utils/__init__.py
hgen/utils/arg_parsing.py
hgen/utils/colors.py
hgen/utils/regexrules.py
hgen/utils/utils.py
hgen-1.0.5.dist-info/LICENSE
hgen-1.0.5.dist-info/METADATA
hgen-1.0.5.dist-info/WHEEL
hgen-1.0.5.dist-info/entry_points.txt
hgen-1.0.5.dist-info/top_level.txt
hgen-1.0.5.dist-info/RECORD
