Metadata-Version: 2.1
Name: hgen
Version: 1.0.5
Summary: a tool to inject prototypes into header from c files
Home-page: https://github.com/scarf005/hgen
Author: scarf
Author-email: greenscarf005@gmail.com
License: UNKNOWN
Platform: UNKNOWN
Classifier: Programming Language :: Python :: 3
Classifier: License :: OSI Approved :: MIT License
Classifier: Operating System :: OS Independent
Classifier: Development Status :: 3 - Alpha
Requires-Python: >=3.8.2
License-File: LICENSE
Requires-Dist: termcolor
